{"team": "早稲田大学", "pitches": [{"pitchType": "ストレート", "velo": 86.6228978, "spinRate": null, "ivb": 24.81147752, "hb": 7.714922604, "px": -0.672801348, "pz": 4.111347495, "result": "nan", "pitchCall": "BallCalled", "batterSide": "Right", "year": 2019}, {"pitchType": "その他", "velo": 74.31380843, "spinRate": null, "ivb": 3.508434366, "hb": -2.662402922, "px": 0.180131355, "pz": 5.019089419, "result": "nan", "pitchCall": "BallCalled", "batterSide": "Right", "year": 2019}, {"pitchType": "ストレート", "velo": 84.17566995, "spinRate": null, "ivb": 16.6339797, "hb": 5.665048627, "px": 0.385975165, "pz": 2.905886272, "result": "nan", "pitchCall": "FoulBall", "batterSide": "Right", "year": 2019}, {"pitchType": "チェンジアップ", "velo": 75.87597482, "spinRate": null, "ivb": 4.837809207, "hb": -0.582701301, "px": null, "pz": 1.961203039, "result": "nan", "pitchCall": "BallCalled", "batterSide": "Right", "year": 2019}, {"pitchType": "チェンジアップ", "velo": 83.70720413, "spinRate": null, "ivb": 19.4063873, "hb": 11.50976138, "px": 0.60596766, "pz": 3.937250746, "result": "nan", "pitchCall": "BallCalled", "batterSide": "Right", "year": 2019}, {"pitchType": "チェンジアップ", "velo": 82.66873698, "spinRate": null, "ivb": 16.69747824, "hb": 12.09629304, "px": 0.218909841, "pz": 1.706025547, "result": "nan", "pitchCall": "StrikeCalled", "batterSide": "Left", "year": 2019}, {"pitchType": "チェンジアップ", "velo": 73.66384707, "spinRate": null, "ivb": 6.68268695, "hb": 12.33741771, "px": -0.178590267, "pz": -0.423674469, "result": "nan", "pitchCall": "BallCalled", "batterSide": "Left", "year": 2019}, {"pitchType": "チェンジアップ", "velo": 82.15836001, "spinRate": null, "ivb": 19.83789066, "hb": 2.576896864, "px": 0.116086605, "pz": 3.367571591, "result": "nan", "pitchCall": "InPlay", "batterSide": "Left", "year": 2019}, {"pitchType": "スライダー", "velo": 76.6972693, "spinRate": null, "ivb": 3.765544336, "hb": -1.48973011, "px": null, "pz": 2.309789383, "result": "nan", "pitchCall": "StrikeCalled", "batterSide": "Left", "year": 2019}, {"pitchType": "チェンジアップ", "velo": 76.31862159, "spinRate": null, "ivb": 5.614107201, "hb": -0.80586906, "px": -0.213044312, "pz": 0.629168153, "result": "nan", "pitchCall": "BallCalled", "batterSide": "Left", "year": 2019}, {"pitchType": "ストレート", "velo": 86.03778432, "spinRate": null, "ivb": 18.7193932, "hb": 10.57652993, "px": 0.164898916, "pz": 1.39982999, "result": "nan", "pitchCall": "StrikeCalled", "batterSide": "Left", "year": 2019}, {"pitchType": "ストレート", "velo": 88.10277734, "spinRate": null, "ivb": 16.69291701, "hb": 9.623516924, "px": -0.380295294, "pz": 1.369476092, "result": "nan", "pitchCall": "BallCalled", "batterSide": "Left", "year": 2019}, {"pitchType": "ストレート", "velo": 86.45518678, "spinRate": null, "ivb": 20.76998161, "hb": 9.352187626, "px": 0.964882605, "pz": 2.5737068, "result": "nan", "pitchCall": "FoulBall", "batterSide": "Left", "year": 2019}, {"pitchType": "ストレート", "velo": 87.04886509, "spinRate": null, "ivb": 17.42698996, "hb": 8.937328588, "px": 0.86991252, "pz": 2.326539755, "result": "nan", "pitchCall": "FoulBall", "batterSide": "Left", "year": 2019}, {"pitchType": "チェンジアップ", "velo": 73.98504163, "spinRate": null, "ivb": 10.27955906, "hb": 14.71636944, "px": 0.726424426, "pz": 1.282336891, "result": "nan", "pitchCall": "StrikeSwinging", "batterSide": "Left", "year": 2019}, {"pitchType": "ストレート", "velo": 87.59179205, "spinRate": null, "ivb": 21.82325106, "hb": 10.61648748, "px": null, "pz": 2.083602639, "result": "nan", "pitchCall": "StrikeCalled", "batterSide": "Right", "year": 2019}, {"pitchType": "ストレート", "velo": 87.56307214, "spinRate": null, "ivb": 21.00277916, "hb": 13.21792328, "px": -0.391734783, "pz": 1.907560691, "result": "nan", "pitchCall": "StrikeCalled", "batterSide": "Right", "year": 2019}, {"pitchType": "ストレート", "velo": 88.49710039, "spinRate": null, "ivb": 22.86276999, "hb": 11.56846129, "px": -0.528830418, "pz": 2.364704333, "result": "nan", "pitchCall": "StrikeSwinging", "batterSide": "Right", "year": 2019}, {"pitchType": "ストレート", "velo": 139.405694345452, "spinRate": 2010.82521, "ivb": 24.81147752, "hb": 7.714922604, "px": -0.672801348, "pz": null, "result": "Undefined", "pitchCall": "BallCalled", "batterSide": "Right", "year": 2019}, {"pitchType": "その他", "velo": 119.596184458736, "spinRate": 1822.318915, "ivb": 3.508434366, "hb": -2.662402922, "px": 0.180131355, "pz": null, "result": "Undefined", "pitchCall": "BallCalled", "batterSide": "Right", "year": 2019}, {"pitchType": "ストレート", "velo": 135.467272677333, "spinRate": 2063.412138, "ivb": 16.6339797, "hb": 5.665048627, "px": 0.385975165, "pz": null, "result": "Undefined", "pitchCall": "FoulBall", "batterSide": "Right", "year": 2019}, {"pitchType": "チェンジアップ", "velo": 122.110241316818, "spinRate": 1856.393877, "ivb": 4.837809207, "hb": -0.582701301, "px": -0.974047906, "pz": 1.961203039, "result": "Undefined", "pitchCall": "BallCalled", "batterSide": "Right", "year": 2019}, {"pitchType": "チェンジアップ", "velo": 134.713351894574, "spinRate": 2044.371556, "ivb": 19.4063873, "hb": 11.50976138, "px": 0.60596766, "pz": null, "result": "Undefined", "pitchCall": "BallCalled", "batterSide": "Right", "year": 2019}, {"pitchType": "チェンジアップ", "velo": 133.042105171393, "spinRate": 1961.150684, "ivb": 16.69747824, "hb": 12.09629304, "px": 0.218909841, "pz": 1.706025547, "result": "Undefined", "pitchCall": "StrikeCalled", "batterSide": "Left", "year": 2019}, {"pitchType": "チェンジアップ", "velo": 118.550175643633, "spinRate": 1602.329332, "ivb": 6.68268695, "hb": 12.33741771, "px": -0.178590267, "pz": -0.423674469, "result": "Undefined", "pitchCall": "BallCalled", "batterSide": "Left", "year": 2019}, {"pitchType": "チェンジアップ", "velo": 132.220735098493, "spinRate": 1997.233072, "ivb": 19.83789066, "hb": 2.576896864, "px": 0.116086605, "pz": null, "result": "Sacrifice", "pitchCall": "InPlay", "batterSide": "Left", "year": 2019}, {"pitchType": "スライダー", "velo": 123.431983375262, "spinRate": 1886.297601, "ivb": 3.765544336, "hb": -1.48973011, "px": -0.929843334, "pz": null, "result": "Undefined", "pitchCall": "StrikeCalled", "batterSide": "Left", "year": 2019}, {"pitchType": "チェンジアップ", "velo": 122.82261046965, "spinRate": 1879.190473, "ivb": 5.614107201, "hb": -0.80586906, "px": -0.213044312, "pz": 0.629168153, "result": "Undefined", "pitchCall": "BallCalled", "batterSide": "Left", "year": 2019}, {"pitchType": "ストレート", "velo": 138.464047817548, "spinRate": 2111.261005, "ivb": 18.7193932, "hb": 10.57652993, "px": 0.164898916, "pz": 1.39982999, "result": "Undefined", "pitchCall": "StrikeCalled", "batterSide": "Left", "year": 2019}, {"pitchType": "ストレート", "velo": 141.787323684355, "spinRate": 2052.019054, "ivb": 16.69291701, "hb": 9.623516924, "px": -0.380295294, "pz": 1.369476092, "result": "Undefined", "pitchCall": "BallCalled", "batterSide": "Left", "year": 2019}, {"pitchType": "ストレート", "velo": 139.135790292525, "spinRate": 2153.183399, "ivb": 20.76998161, "hb": 9.352187626, "px": 0.964882605, "pz": null, "result": "Undefined", "pitchCall": "FoulBall", "batterSide": "Left", "year": 2019}, {"pitchType": "ストレート", "velo": 140.09122054394, "spinRate": 2046.07815, "ivb": 17.42698996, "hb": 8.937328588, "px": 0.86991252, "pz": null, "result": "Undefined", "pitchCall": "FoulBall", "batterSide": "Left", "year": 2019}, {"pitchType": "チェンジアップ", "velo": 119.067086896824, "spinRate": 1411.616346, "ivb": 10.27955906, "hb": 14.71636944, "px": 0.726424426, "pz": 1.282336891, "result": "Undefined", "pitchCall": "StrikeSwinging", "batterSide": "Left", "year": 2019}, {"pitchType": "ストレート", "velo": 140.964974617747, "spinRate": 2060.789529, "ivb": 21.82325106, "hb": 10.61648748, "px": -0.995840048, "pz": 2.083602639, "result": "Undefined", "pitchCall": "StrikeCalled", "batterSide": "Right", "year": 2019}, {"pitchType": "ストレート", "velo": 140.918754517787, "spinRate": 2127.715163, "ivb": 21.00277916, "hb": 13.21792328, "px": -0.391734783, "pz": 1.907560691, "result": "Undefined", "pitchCall": "StrikeCalled", "batterSide": "Right", "year": 2019}, {"pitchType": "ストレート", "velo": 142.421923541642, "spinRate": 2126.844131, "ivb": 22.86276999, "hb": 11.56846129, "px": -0.528830418, "pz": null, "result": "Undefined", "pitchCall": "StrikeSwinging", "batterSide": "Right", "year": 2019}, {"pitchType": "チェンジアップ", "velo": 134.583143204639, "spinRate": 2021.8156, "ivb": 22.86128922, "hb": 8.788594315, "px": -0.779528683, "pz": null, "result": "Undefined", "pitchCall": "StrikeSwinging", "batterSide": "Right", "year": 2019}, {"pitchType": "ストレート", "velo": 138.865463288952, "spinRate": 2180.632772, "ivb": 18.13293333, "hb": 8.723007264, "px": null, "pz": null, "result": "Undefined", "pitchCall": "BallCalled", "batterSide": "Right", "year": 2019}, {"pitchType": "チェンジアップ", "velo": 115.048865235761, "spinRate": 1409.295308, "ivb": 11.91174689, "hb": 9.339501095, "px": 0.069347827, "pz": 0.802427358, "result": "Undefined", "pitchCall": "BallCalled", "batterSide": "Right", "year": 2019}, {"pitchType": "チェンジアップ", "velo": 132.549243525014, "spinRate": 2079.128502, "ivb": 20.5821705, "hb": 7.943996495, "px": -0.216544702, "pz": 1.600279499, "result": "Undefined", "pitchCall": "StrikeCalled", "batterSide": "Right", "year": 2019}, {"pitchType": "ストレート", "velo": 141.771331431374, "spinRate": 2187.166457, "ivb": 21.84437978, "hb": 5.784882617, "px": null, "pz": null, "result": "Undefined", "pitchCall": "BallCalled", "batterSide": "Right", "year": 2019}, {"pitchType": "ストレート", "velo": 138.764653716364, "spinRate": 2128.810835, "ivb": 23.17897838, "hb": 5.155624509, "px": -0.546951616, "pz": null, "result": "Out", "pitchCall": "InPlay", "batterSide": "Right", "year": 2019}, {"pitchType": "ストレート", "velo": 141.767712299302, "spinRate": 2174.296762, "ivb": 23.01042084, "hb": 9.532703995, "px": 0.163701015, "pz": null, "result": "Undefined", "pitchCall": "StrikeSwinging", "batterSide": "Left", "year": 2019}, {"pitchType": "ストレート", "velo": 144.267321629403, "spinRate": 2249.907619, "ivb": 22.97627885, "hb": 9.314617319, "px": -0.080501543, "pz": null, "result": "Undefined", "pitchCall": "StrikeSwinging", "batterSide": "Left", "year": 2019}, {"pitchType": "ストレート", "velo": 143.896666133248, "spinRate": 2190.487536, "ivb": 18.25949078, "hb": 7.920747436, "px": 1.081769946, "pz": null, "result": "Out", "pitchCall": "InPlay", "batterSide": "Left", "year": 2019}, {"pitchType": "ストレート", "velo": 143.717150017685, "spinRate": 2229.890528, "ivb": 20.58195459, "hb": 10.62047631, "px": 0.31413843, "pz": null, "result": "Undefined", "pitchCall": "BallCalled", "batterSide": "Right", "year": 2019}, {"pitchType": "ストレート", "velo": 142.359257049047, "spinRate": 2197.639966, "ivb": 23.73116647, "hb": 10.18168848, "px": -0.307000137, "pz": null, "result": "Undefined", "pitchCall": "StrikeSwinging", "batterSide": "Right", "year": 2019}, {"pitchType": "ストレート", "velo": 139.835070924538, "spinRate": 2213.334383, "ivb": 20.7393455, "hb": 11.65904244, "px": 0.33909515, "pz": 1.987674844, "result": "Undefined", "pitchCall": "FoulBall", "batterSide": "Right", "year": 2019}, {"pitchType": "ストレート", "velo": 145.465530588512, "spinRate": 2084.964702, "ivb": 13.95713059, "hb": 5.715529848, "px": -0.760651097, "pz": null, "result": "Undefined", "pitchCall": "StrikeSwinging", "batterSide": "Right", "year": 2019}, {"pitchType": "チェンジアップ", "velo": 134.583143204639, "spinRate": 2021.8156, "ivb": 22.86128922, "hb": 8.788594315, "px": -0.779528683, "pz": null, "result": "Undefined", "pitchCall": "StrikeSwinging", "batterSide": "Right", "year": 2019}, {"pitchType": "ストレート", "velo": 138.865463288952, "spinRate": 2180.632772, "ivb": 18.13293333, "hb": 8.723007264, "px": null, "pz": null, "result": "Undefined", "pitchCall": "BallCalled", "batterSide": "Right", "year": 2019}, {"pitchType": "チェンジアップ", "velo": 115.048865235761, "spinRate": 1409.295308, "ivb": 11.91174689, "hb": 9.339501095, "px": 0.069347827, "pz": 0.802427358, "result": "Undefined", "pitchCall": "BallCalled", "batterSide": "Right", "year": 2019}, {"pitchType": "チェンジアップ", "velo": 132.549243525014, "spinRate": 2079.128502, "ivb": 20.5821705, "hb": 7.943996495, "px": -0.216544702, "pz": 1.600279499, "result": "Undefined", "pitchCall": "StrikeCalled", "batterSide": "Right", "year": 2019}, {"pitchType": "ストレート", "velo": 141.771331431374, "spinRate": 2187.166457, "ivb": 21.84437978, "hb": 5.784882617, "px": null, "pz": null, "result": "Undefined", "pitchCall": "BallCalled", "batterSide": "Right", "year": 2019}, {"pitchType": "ストレート", "velo": 138.764653716364, "spinRate": 2128.810835, "ivb": 23.17897838, "hb": 5.155624509, "px": -0.546951616, "pz": null, "result": "Out", "pitchCall": "InPlay", "batterSide": "Right", "year": 2019}, {"pitchType": "ストレート", "velo": 141.767712299302, "spinRate": 2174.296762, "ivb": 23.01042084, "hb": 9.532703995, "px": 0.163701015, "pz": null, "result": "Undefined", "pitchCall": "StrikeSwinging", "batterSide": "Left", "year": 2019}, {"pitchType": "ストレート", "velo": 144.267321629403, "spinRate": 2249.907619, "ivb": 22.97627885, "hb": 9.314617319, "px": -0.080501543, "pz": null, "result": "Undefined", "pitchCall": "StrikeSwinging", "batterSide": "Left", "year": 2019}, {"pitchType": "ストレート", "velo": 143.896666133248, "spinRate": 2190.487536, "ivb": 18.25949078, "hb": 7.920747436, "px": 1.081769946, "pz": null, "result": "Out", "pitchCall": "InPlay", "batterSide": "Left", "year": 2019}, {"pitchType": "ストレート", "velo": 143.717150017685, "spinRate": 2229.890528, "ivb": 20.58195459, "hb": 10.62047631, "px": 0.31413843, "pz": null, "result": "Undefined", "pitchCall": "BallCalled", "batterSide": "Right", "year": 2019}, {"pitchType": "ストレート", "velo": 142.359257049047, "spinRate": 2197.639966, "ivb": 23.73116647, "hb": 10.18168848, "px": -0.307000137, "pz": null, "result": "Undefined", "pitchCall": "StrikeSwinging", "batterSide": "Right", "year": 2019}, {"pitchType": "ストレート", "velo": 139.835070924538, "spinRate": 2213.334383, "ivb": 20.7393455, "hb": 11.65904244, "px": 0.33909515, "pz": 1.987674844, "result": "Undefined", "pitchCall": "FoulBall", "batterSide": "Right", "year": 2019}, {"pitchType": "ストレート", "velo": 145.465530588512, "spinRate": 2084.964702, "ivb": 13.95713059, "hb": 5.715529848, "px": -0.760651097, "pz": null, "result": "Undefined", "pitchCall": "StrikeSwinging", "batterSide": "Right", "year": 2019}, {"pitchType": "ストレート", "velo": 135.727629159775, "spinRate": 1841.717001, "ivb": 20.61256919, "hb": 10.18839687, "px": -0.275609894, "pz": null, "result": "Out", "pitchCall": "InPlay", "batterSide": "Right", "year": 2019}, {"pitchType": "チェンジアップ", "velo": 121.762955352578, "spinRate": 1761.758528, "ivb": 6.671795208, "hb": 0.502954617, "px": -0.032611924, "pz": null, "result": "Undefined", "pitchCall": "StrikeCalled", "batterSide": "Right", "year": 2019}, {"pitchType": "ストレート", "velo": 142.688677166678, "spinRate": 2099.158348, "ivb": 21.14362763, "hb": 11.02480777, "px": null, "pz": null, "result": "Undefined", "pitchCall": "BallCalled", "batterSide": "Right", "year": 2019}, {"pitchType": "ストレート", "velo": 140.425945368079, "spinRate": 2106.611319, "ivb": 20.79843556, "hb": 10.03369457, "px": -1.30820712, "pz": null, "result": "Out", "pitchCall": "InPlay", "batterSide": "Right", "year": 2019}, {"pitchType": "その他", "velo": 100.119661791761, "spinRate": 1278.020976, "ivb": -0.429670864, "hb": 7.213325227, "px": -0.066429623, "pz": 0.991780049, "result": "Undefined", "pitchCall": "BallCalled", "batterSide": "Left", "year": 2019}, {"pitchType": "ストレート", "velo": 139.302356805497, "spinRate": 2046.348934, "ivb": 20.23095298, "hb": 12.28210371, "px": 0.786135828, "pz": null, "result": "Undefined", "pitchCall": "StrikeCalled", "batterSide": "Left", "year": 2019}, {"pitchType": "ストレート", "velo": 141.611917469098, "spinRate": 2163.568903, "ivb": 20.29563749, "hb": 12.42505782, "px": -1.155729607, "pz": 1.93975797, "result": "Undefined", "pitchCall": "BallCalled", "batterSide": "Left", "year": 2019}, {"pitchType": "ストレート", "velo": 137.862035759509, "spinRate": 2146.875024, "ivb": 16.64142091, "hb": 9.67521384, "px": 0.486471466, "pz": null, "result": "Undefined", "pitchCall": "FoulBall", "batterSide": "Left", "year": 2019}, {"pitchType": "ストレート", "velo": 143.684117187647, "spinRate": 2129.057093, "ivb": 19.46723956, "hb": 13.56436411, "px": 0.012796618, "pz": 1.898552988, "result": "Undefined", "pitchCall": "FoulBall", "batterSide": "Left", "year": 2019}, {"pitchType": "ストレート", "velo": 143.547586672231, "spinRate": 2011.927685, "ivb": 16.54188031, "hb": 10.16396801, "px": -0.208580754, "pz": null, "result": "Double", "pitchCall": "InPlay", "batterSide": "Left", "year": 2019}, {"pitchType": "チェンジアップ", "velo": 119.289996226169, "spinRate": 1632.475351, "ivb": 3.814642946, "hb": 0.557805024, "px": 0.43329551, "pz": null, "result": "Undefined", "pitchCall": "StrikeCalled", "batterSide": "Left", "year": 2019}, {"pitchType": "ストレート", "velo": 141.46479223394, "spinRate": 1980.125518, "ivb": 21.09936228, "hb": 8.607952472, "px": 0.190215783, "pz": null, "result": "Undefined", "pitchCall": "FoulBall", "batterSide": "Left", "year": 2019}, {"pitchType": "ストレート", "velo": 143.6218534002, "spinRate": 2064.595456, "ivb": 18.50782418, "hb": 8.56601818, "px": null, "pz": 2.10062984, "result": "Undefined", "pitchCall": "BallCalled", "batterSide": "Left", "year": 2019}, {"pitchType": "ストレート", "velo": 142.439050588537, "spinRate": 2086.064163, "ivb": 17.41863349, "hb": 11.01908833, "px": 0.654013375, "pz": null, "result": "Out", "pitchCall": "InPlay", "batterSide": "Left", "year": 2019}, {"pitchType": "ストレート", "velo": 136.290137633972, "spinRate": 1980.448835, "ivb": 27.72175867, "hb": 7.152978336, "px": null, "pz": null, "result": "Undefined", "pitchCall": "BallCalled", "batterSide": "Left", "year": 2019}, {"pitchType": "ストレート", "velo": 135.384111175464, "spinRate": 2081.869733, "ivb": 25.48709624, "hb": 7.216555458, "px": 0.36131979, "pz": null, "result": "Undefined", "pitchCall": "StrikeCalled", "batterSide": "Left", "year": 2019}, {"pitchType": "ストレート", "velo": 137.668321740692, "spinRate": 2019.019579, "ivb": 23.42243195, "hb": 6.2553386, "px": 1.035831287, "pz": null, "result": "Undefined", "pitchCall": "StrikeCalled", "batterSide": "Left", "year": 2019}, {"pitchType": "ストレート", "velo": 141.689062018854, "spinRate": 2071.352706, "ivb": 21.1922222, "hb": 4.644229105, "px": 0.003479261, "pz": null, "result": "Undefined", "pitchCall": "FoulBall", "batterSide": "Left", "year": 2019}, {"pitchType": "ストレート", "velo": 142.453713269184, "spinRate": 2147.087499, "ivb": 18.88328908, "hb": 0.792217725, "px": -0.193551, "pz": null, "result": "Undefined", "pitchCall": "FoulBall", "batterSide": "Left", "year": 2019}, {"pitchType": "ストレート", "velo": 140.860627265223, "spinRate": 1914.064688, "ivb": 20.53692912, "hb": 5.526065074, "px": 0.359216052, "pz": null, "result": "Single", "pitchCall": "InPlay", "batterSide": "Left", "year": 2019}, {"pitchType": "ストレート", "velo": 136.859076725033, "spinRate": 1923.407982, "ivb": 16.65925336, "hb": 10.03714023, "px": 1.399474944, "pz": null, "result": "Undefined", "pitchCall": "BallCalled", "batterSide": "Left", "year": 2019}, {"pitchType": "チェンジアップ", "velo": 135.07102674397, "spinRate": 1917.989155, "ivb": 21.5128445, "hb": 11.93266701, "px": -0.533666592, "pz": null, "result": "Undefined", "pitchCall": "StrikeCalled", "batterSide": "Left", "year": 2019}, {"pitchType": "チェンジアップ", "velo": 114.895112271775, "spinRate": 1285.257842, "ivb": 8.252828963, "hb": 8.930406939, "px": 0.282810141, "pz": 1.969051162, "result": "Undefined", "pitchCall": "StrikeSwinging", "batterSide": "Left", "year": 2019}, {"pitchType": "ストレート", "velo": 140.930683831004, "spinRate": 1877.561516, "ivb": 20.4932538, "hb": 9.121111411, "px": 0.915300298, "pz": null, "result": "Undefined", "pitchCall": "FoulBall", "batterSide": "Left", "year": 2019}, {"pitchType": "チェンジアップ", "velo": 116.13723171873, "spinRate": 1306.261599, "ivb": 8.67026234, "hb": 10.32684912, "px": 0.56581245, "pz": 1.054071216, "result": "Undefined", "pitchCall": "BallCalled", "batterSide": "Left", "year": 2019}, {"pitchType": "チェンジアップ", "velo": 122.428028642128, "spinRate": 1803.343536, "ivb": 5.909453408, "hb": -1.215723439, "px": -0.937829714, "pz": 1.550613599, "result": "Undefined", "pitchCall": "StrikeSwinging", "batterSide": "Left", "year": 2019}, {"pitchType": "チェンジアップ", "velo": 120.438916090032, "spinRate": 1777.972575, "ivb": 4.480775121, "hb": -0.061548221, "px": -0.584370303, "pz": null, "result": "Undefined", "pitchCall": "StrikeCalled", "batterSide": "Right", "year": 2019}, {"pitchType": "チェンジアップ", "velo": 117.162731458927, "spinRate": 1528.606429, "ivb": 12.32643818, "hb": 8.286765831, "px": -1.362870821, "pz": -0.507379927, "result": "Undefined", "pitchCall": "BallCalled", "batterSide": "Right", "year": 2019}, {"pitchType": "ストレート", "velo": 136.905878392188, "spinRate": 1963.095457, "ivb": 22.7271479, "hb": 7.835242893, "px": -1.207970496, "pz": 1.586643303, "result": "Undefined", "pitchCall": "BallCalled", "batterSide": "Right", "year": 2019}, {"pitchType": "チェンジアップ", "velo": 122.274014144298, "spinRate": 1861.694254, "ivb": 7.788645225, "hb": -0.750223069, "px": -0.776948891, "pz": 1.001134748, "result": "Undefined", "pitchCall": "BallCalled", "batterSide": "Right", "year": 2019}, {"pitchType": "ストレート", "velo": 136.645251814213, "spinRate": 2010.111889, "ivb": 16.22273513, "hb": 5.153717033, "px": -0.194558704, "pz": null, "result": "Out", "pitchCall": "InPlay", "batterSide": "Right", "year": 2019}, {"pitchType": "ストレート", "velo": 139.594339603098, "spinRate": 2036.59185, "ivb": 20.26507083, "hb": 8.290892351, "px": 1.261246005, "pz": null, "result": "Undefined", "pitchCall": "StrikeCalled", "batterSide": "Left", "year": 2019}, {"pitchType": "ストレート", "velo": 143.228207902783, "spinRate": 2113.310078, "ivb": 19.08609807, "hb": 11.43220576, "px": -0.566124259, "pz": null, "result": "Undefined", "pitchCall": "FoulBall", "batterSide": "Left", "year": 2019}, {"pitchType": "ストレート", "velo": 144.124150269037, "spinRate": 1945.436576, "ivb": 16.90117477, "hb": 8.071470041, "px": null, "pz": null, "result": "Undefined", "pitchCall": "BallCalled", "batterSide": "Left", "year": 2019}, {"pitchType": "チェンジアップ", "velo": 119.098867145353, "spinRate": 1346.136281, "ivb": 9.808862527, "hb": 10.90353685, "px": -0.412541036, "pz": null, "result": "Out", "pitchCall": "InPlay", "batterSide": "Left", "year": 2019}, {"pitchType": "チェンジアップ", "velo": 122.271500419592, "spinRate": 1575.724464, "ivb": 4.050602887, "hb": 2.04525928, "px": 0.071322439, "pz": 2.055114708, "result": "Undefined", "pitchCall": "StrikeCalled", "batterSide": "Right", "year": 2019}, {"pitchType": "スライダー", "velo": 124.60860455105, "spinRate": 1759.541341, "ivb": 4.267120291, "hb": 1.796677444, "px": -0.757938134, "pz": null, "result": "Undefined", "pitchCall": "FoulBall", "batterSide": "Right", "year": 2019}, {"pitchType": "ストレート", "velo": 145.345732139675, "spinRate": 1982.012545, "ivb": 23.09790522, "hb": 6.857027964, "px": -0.939251202, "pz": null, "result": "Undefined", "pitchCall": "BallCalled", "batterSide": "Right", "year": 2019}, {"pitchType": "ストレート", "velo": 142.463550923203, "spinRate": 1991.856042, "ivb": 21.44828462, "hb": 9.590352629, "px": -0.783838723, "pz": null, "result": "Undefined", "pitchCall": "FoulBall", "batterSide": "Right", "year": 2019}, {"pitchType": "ストレート", "velo": 145.207072097291, "spinRate": 2087.976458, "ivb": 21.29472334, "hb": 13.2177837, "px": -1.27497255, "pz": null, "result": "Undefined", "pitchCall": "BallCalled", "batterSide": "Right", "year": 2019}, {"pitchType": "チェンジアップ", "velo": 115.277153413908, "spinRate": 1226.390963, "ivb": 13.0870307, "hb": 5.900907504, "px": -1.028451901, "pz": 1.545755124, "result": "Out", "pitchCall": "InPlay", "batterSide": "Right", "year": 2019}, {"pitchType": "スライダー", "velo": 125.666305285626, "spinRate": 1831.108625, "ivb": 3.745639548, "hb": -3.054694085, "px": 0.112553724, "pz": null, "result": "Undefined", "pitchCall": "FoulBall", "batterSide": "Right", "year": 2019}, {"pitchType": "チェンジアップ", "velo": 102.481674466976, "spinRate": 2154.629416, "ivb": 7.512215514, "hb": 7.140165261, "px": -0.24398087, "pz": 1.685087587, "result": "Undefined", "pitchCall": "StrikeSwinging", "batterSide": "Right", "year": 2019}, {"pitchType": "ストレート", "velo": 145.122599675339, "spinRate": 2018.777048, "ivb": 24.16845084, "hb": 8.973216026, "px": -0.743548137, "pz": null, "result": "Undefined", "pitchCall": "StrikeSwinging", "batterSide": "Right", "year": 2019}, {"pitchType": "ストレート", "velo": 139.042297970488, "spinRate": 1987.789695, "ivb": 20.78608018, "hb": 6.937139334, "px": -0.717315124, "pz": null, "result": "Undefined", "pitchCall": "BallCalled", "batterSide": "Right", "year": 2019}, {"pitchType": "ストレート", "velo": 138.129378322518, "spinRate": 1960.767396, "ivb": 19.99437656, "hb": 5.474052393, "px": -0.704218386, "pz": null, "result": "Undefined", "pitchCall": "FoulBall", "batterSide": "Right", "year": 2019}, {"pitchType": "スライダー", "velo": 125.255252362099, "spinRate": 1872.575291, "ivb": 6.055781855, "hb": -3.709815794, "px": -0.970169111, "pz": null, "result": "Out", "pitchCall": "InPlay", "batterSide": "Right", "year": 2019}, {"pitchType": "ストレート", "velo": 135.727629159775, "spinRate": 1841.717001, "ivb": 20.61256919, "hb": 10.18839687, "px": -0.275609894, "pz": null, "result": "Out", "pitchCall": "InPlay", "batterSide": "Right", "year": 2019}, {"pitchType": "チェンジアップ", "velo": 121.762955352578, "spinRate": 1761.758528, "ivb": 6.671795208, "hb": 0.502954617, "px": -0.032611924, "pz": null, "result": "Undefined", "pitchCall": "StrikeCalled", "batterSide": "Right", "year": 2019}, {"pitchType": "ストレート", "velo": 142.688677166678, "spinRate": 2099.158348, "ivb": 21.14362763, "hb": 11.02480777, "px": null, "pz": null, "result": "Undefined", "pitchCall": "BallCalled", "batterSide": "Right", "year": 2019}, {"pitchType": "ストレート", "velo": 140.425945368079, "spinRate": 2106.611319, "ivb": 20.79843556, "hb": 10.03369457, "px": -1.30820712, "pz": null, "result": "Out", "pitchCall": "InPlay", "batterSide": "Right", "year": 2019}, {"pitchType": "その他", "velo": 100.119661791761, "spinRate": 1278.020976, "ivb": -0.429670864, "hb": 7.213325227, "px": -0.066429623, "pz": 0.991780049, "result": "Undefined", "pitchCall": "BallCalled", "batterSide": "Left", "year": 2019}, {"pitchType": "ストレート", "velo": 139.302356805497, "spinRate": 2046.348934, "ivb": 20.23095298, "hb": 12.28210371, "px": 0.786135828, "pz": null, "result": "Undefined", "pitchCall": "StrikeCalled", "batterSide": "Left", "year": 2019}, {"pitchType": "ストレート", "velo": 141.611917469098, "spinRate": 2163.568903, "ivb": 20.29563749, "hb": 12.42505782, "px": -1.155729607, "pz": 1.93975797, "result": "Undefined", "pitchCall": "BallCalled", "batterSide": "Left", "year": 2019}, {"pitchType": "ストレート", "velo": 137.862035759509, "spinRate": 2146.875024, "ivb": 16.64142091, "hb": 9.67521384, "px": 0.486471466, "pz": null, "result": "Undefined", "pitchCall": "FoulBall", "batterSide": "Left", "year": 2019}, {"pitchType": "ストレート", "velo": 143.684117187647, "spinRate": 2129.057093, "ivb": 19.46723956, "hb": 13.56436411, "px": 0.012796618, "pz": 1.898552988, "result": "Undefined", "pitchCall": "FoulBall", "batterSide": "Left", "year": 2019}, {"pitchType": "ストレート", "velo": 143.547586672231, "spinRate": 2011.927685, "ivb": 16.54188031, "hb": 10.16396801, "px": -0.208580754, "pz": null, "result": "Double", "pitchCall": "InPlay", "batterSide": "Left", "year": 2019}, {"pitchType": "チェンジアップ", "velo": 119.289996226169, "spinRate": 1632.475351, "ivb": 3.814642946, "hb": 0.557805024, "px": 0.43329551, "pz": null, "result": "Undefined", "pitchCall": "StrikeCalled", "batterSide": "Left", "year": 2019}, {"pitchType": "ストレート", "velo": 141.46479223394, "spinRate": 1980.125518, "ivb": 21.09936228, "hb": 8.607952472, "px": 0.190215783, "pz": null, "result": "Undefined", "pitchCall": "FoulBall", "batterSide": "Left", "year": 2019}, {"pitchType": "ストレート", "velo": 143.6218534002, "spinRate": 2064.595456, "ivb": 18.50782418, "hb": 8.56601818, "px": null, "pz": 2.10062984, "result": "Undefined", "pitchCall": "BallCalled", "batterSide": "Left", "year": 2019}, {"pitchType": "ストレート", "velo": 142.439050588537, "spinRate": 2086.064163, "ivb": 17.41863349, "hb": 11.01908833, "px": 0.654013375, "pz": null, "result": "Out", "pitchCall": "InPlay", "batterSide": "Left", "year": 2019}, {"pitchType": "ストレート", "velo": 136.290137633972, "spinRate": 1980.448835, "ivb": 27.72175867, "hb": 7.152978336, "px": null, "pz": null, "result": "Undefined", "pitchCall": "BallCalled", "batterSide": "Left", "year": 2019}, {"pitchType": "ストレート", "velo": 135.384111175464, "spinRate": 2081.869733, "ivb": 25.48709624, "hb": 7.216555458, "px": 0.36131979, "pz": null, "result": "Undefined", "pitchCall": "StrikeCalled", "batterSide": "Left", "year": 2019}, {"pitchType": "ストレート", "velo": 137.668321740692, "spinRate": 2019.019579, "ivb": 23.42243195, "hb": 6.2553386, "px": 1.035831287, "pz": null, "result": "Undefined", "pitchCall": "StrikeCalled", "batterSide": "Left", "year": 2019}, {"pitchType": "ストレート", "velo": 141.689062018854, "spinRate": 2071.352706, "ivb": 21.1922222, "hb": 4.644229105, "px": 0.003479261, "pz": null, "result": "Undefined", "pitchCall": "FoulBall", "batterSide": "Left", "year": 2019}, {"pitchType": "ストレート", "velo": 142.453713269184, "spinRate": 2147.087499, "ivb": 18.88328908, "hb": 0.792217725, "px": -0.193551, "pz": null, "result": "Undefined", "pitchCall": "FoulBall", "batterSide": "Left", "year": 2019}, {"pitchType": "ストレート", "velo": 140.860627265223, "spinRate": 1914.064688, "ivb": 20.53692912, "hb": 5.526065074, "px": 0.359216052, "pz": null, "result": "Single", "pitchCall": "InPlay", "batterSide": "Left", "year": 2019}, {"pitchType": "ストレート", "velo": 136.859076725033, "spinRate": 1923.407982, "ivb": 16.65925336, "hb": 10.03714023, "px": 1.399474944, "pz": null, "result": "Undefined", "pitchCall": "BallCalled", "batterSide": "Left", "year": 2019}, {"pitchType": "チェンジアップ", "velo": 135.07102674397, "spinRate": 1917.989155, "ivb": 21.5128445, "hb": 11.93266701, "px": -0.533666592, "pz": null, "result": "Undefined", "pitchCall": "StrikeCalled", "batterSide": "Left", "year": 2019}, {"pitchType": "チェンジアップ", "velo": 114.895112271775, "spinRate": 1285.257842, "ivb": 8.252828963, "hb": 8.930406939, "px": 0.282810141, "pz": 1.969051162, "result": "Undefined", "pitchCall": "StrikeSwinging", "batterSide": "Left", "year": 2019}, {"pitchType": "ストレート", "velo": 140.930683831004, "spinRate": 1877.561516, "ivb": 20.4932538, "hb": 9.121111411, "px": 0.915300298, "pz": null, "result": "Undefined", "pitchCall": "FoulBall", "batterSide": "Left", "year": 2019}, {"pitchType": "チェンジアップ", "velo": 116.13723171873, "spinRate": 1306.261599, "ivb": 8.67026234, "hb": 10.32684912, "px": 0.56581245, "pz": 1.054071216, "result": "Undefined", "pitchCall": "BallCalled", "batterSide": "Left", "year": 2019}, {"pitchType": "チェンジアップ", "velo": 122.428028642128, "spinRate": 1803.343536, "ivb": 5.909453408, "hb": -1.215723439, "px": -0.937829714, "pz": 1.550613599, "result": "Undefined", "pitchCall": "StrikeSwinging", "batterSide": "Left", "year": 2019}, {"pitchType": "チェンジアップ", "velo": 120.438916090032, "spinRate": 1777.972575, "ivb": 4.480775121, "hb": -0.061548221, "px": -0.584370303, "pz": null, "result": "Undefined", "pitchCall": "StrikeCalled", "batterSide": "Right", "year": 2019}, {"pitchType": "チェンジアップ", "velo": 117.162731458927, "spinRate": 1528.606429, "ivb": 12.32643818, "hb": 8.286765831, "px": -1.362870821, "pz": -0.507379927, "result": "Undefined", "pitchCall": "BallCalled", "batterSide": "Right", "year": 2019}, {"pitchType": "ストレート", "velo": 136.905878392188, "spinRate": 1963.095457, "ivb": 22.7271479, "hb": 7.835242893, "px": -1.207970496, "pz": 1.586643303, "result": "Undefined", "pitchCall": "BallCalled", "batterSide": "Right", "year": 2019}, {"pitchType": "チェンジアップ", "velo": 122.274014144298, "spinRate": 1861.694254, "ivb": 7.788645225, "hb": -0.750223069, "px": -0.776948891, "pz": 1.001134748, "result": "Undefined", "pitchCall": "BallCalled", "batterSide": "Right", "year": 2019}, {"pitchType": "ストレート", "velo": 136.645251814213, "spinRate": 2010.111889, "ivb": 16.22273513, "hb": 5.153717033, "px": -0.194558704, "pz": null, "result": "Out", "pitchCall": "InPlay", "batterSide": "Right", "year": 2019}, {"pitchType": "ストレート", "velo": 139.594339603098, "spinRate": 2036.59185, "ivb": 20.26507083, "hb": 8.290892351, "px": 1.261246005, "pz": null, "result": "Undefined", "pitchCall": "StrikeCalled", "batterSide": "Left", "year": 2019}, {"pitchType": "ストレート", "velo": 143.228207902783, "spinRate": 2113.310078, "ivb": 19.08609807, "hb": 11.43220576, "px": -0.566124259, "pz": null, "result": "Undefined", "pitchCall": "FoulBall", "batterSide": "Left", "year": 2019}, {"pitchType": "ストレート", "velo": 144.124150269037, "spinRate": 1945.436576, "ivb": 16.90117477, "hb": 8.071470041, "px": null, "pz": null, "result": "Undefined", "pitchCall": "BallCalled", "batterSide": "Left", "year": 2019}, {"pitchType": "チェンジアップ", "velo": 119.098867145353, "spinRate": 1346.136281, "ivb": 9.808862527, "hb": 10.90353685, "px": -0.412541036, "pz": null, "result": "Out", "pitchCall": "InPlay", "batterSide": "Left", "year": 2019}, {"pitchType": "チェンジアップ", "velo": 122.271500419592, "spinRate": 1575.724464, "ivb": 4.050602887, "hb": 2.04525928, "px": 0.071322439, "pz": 2.055114708, "result": "Undefined", "pitchCall": "StrikeCalled", "batterSide": "Right", "year": 2019}, {"pitchType": "スライダー", "velo": 124.60860455105, "spinRate": 1759.541341, "ivb": 4.267120291, "hb": 1.796677444, "px": -0.757938134, "pz": null, "result": "Undefined", "pitchCall": "FoulBall", "batterSide": "Right", "year": 2019}, {"pitchType": "ストレート", "velo": 145.345732139675, "spinRate": 1982.012545, "ivb": 23.09790522, "hb": 6.857027964, "px": -0.939251202, "pz": null, "result": "Undefined", "pitchCall": "BallCalled", "batterSide": "Right", "year": 2019}, {"pitchType": "ストレート", "velo": 142.463550923203, "spinRate": 1991.856042, "ivb": 21.44828462, "hb": 9.590352629, "px": -0.783838723, "pz": null, "result": "Undefined", "pitchCall": "FoulBall", "batterSide": "Right", "year": 2019}, {"pitchType": "ストレート", "velo": 145.207072097291, "spinRate": 2087.976458, "ivb": 21.29472334, "hb": 13.2177837, "px": -1.27497255, "pz": null, "result": "Undefined", "pitchCall": "BallCalled", "batterSide": "Right", "year": 2019}, {"pitchType": "チェンジアップ", "velo": 115.277153413908, "spinRate": 1226.390963, "ivb": 13.0870307, "hb": 5.900907504, "px": -1.028451901, "pz": 1.545755124, "result": "Out", "pitchCall": "InPlay", "batterSide": "Right", "year": 2019}, {"pitchType": "スライダー", "velo": 125.666305285626, "spinRate": 1831.108625, "ivb": 3.745639548, "hb": -3.054694085, "px": 0.112553724, "pz": null, "result": "Undefined", "pitchCall": "FoulBall", "batterSide": "Right", "year": 2019}, {"pitchType": "チェンジアップ", "velo": 102.481674466976, "spinRate": 2154.629416, "ivb": 7.512215514, "hb": 7.140165261, "px": -0.24398087, "pz": 1.685087587, "result": "Undefined", "pitchCall": "Undefined", "batterSide": "Right", "year": 2019}, {"pitchType": "ストレート", "velo": 145.122599675339, "spinRate": 2018.777048, "ivb": 24.16845084, "hb": 8.973216026, "px": -0.743548137, "pz": null, "result": "Undefined", "pitchCall": "StrikeSwinging", "batterSide": "Right", "year": 2019}, {"pitchType": "ストレート", "velo": 139.042297970488, "spinRate": 1987.789695, "ivb": 20.78608018, "hb": 6.937139334, "px": -0.717315124, "pz": null, "result": "Undefined", "pitchCall": "BallCalled", "batterSide": "Right", "year": 2019}, {"pitchType": "ストレート", "velo": 138.129378322518, "spinRate": 1960.767396, "ivb": 19.99437656, "hb": 5.474052393, "px": -0.704218386, "pz": null, "result": "Undefined", "pitchCall": "FoulBall", "batterSide": "Right", "year": 2019}, {"pitchType": "スライダー", "velo": 125.255252362099, "spinRate": 1872.575291, "ivb": 6.055781855, "hb": -3.709815794, "px": -0.970169111, "pz": null, "result": "Out", "pitchCall": "InPlay", "batterSide": "Right", "year": 2019}], "batted": [{"direction": null, "distance": null, "ev": null, "la": null, "result": "nan", "batterSide": "Left", "year": 2019}, {"direction": null, "distance": null, "ev": null, "la": null, "result": "Sacrifice", "batterSide": "Left", "year": 2019}, {"direction": null, "distance": null, "ev": null, "la": null, "result": "Out", "batterSide": "Right", "year": 2019}, {"direction": -2.018013119, "distance": null, "ev": 122.941089195313, "la": 43.13860458, "result": "Out", "batterSide": "Left", "year": 2019}, {"direction": null, "distance": null, "ev": null, "la": null, "result": "Out", "batterSide": "Right", "year": 2019}, {"direction": -2.018013119, "distance": null, "ev": 122.941089195313, "la": 43.13860458, "result": "Out", "batterSide": "Left", "year": 2019}, {"direction": null, "distance": null, "ev": null, "la": null, "result": "Out", "batterSide": "Right", "year": 2019}, {"direction": 45.66528506, "distance": null, "ev": 134.81038603599, "la": 40.60681947, "result": "Out", "batterSide": "Right", "year": 2019}, {"direction": 35.17722204, "distance": null, "ev": 160.930041522495, "la": 23.08053963, "result": "Double", "batterSide": "Left", "year": 2019}, {"direction": 6.545530443, "distance": null, "ev": 145.737080593924, "la": 45.34574741, "result": "Out", "batterSide": "Left", "year": 2019}, {"direction": -23.80820318, "distance": null, "ev": 125.844477827597, "la": 15.98576157, "result": "Single", "batterSide": "Left", "year": 2019}, {"direction": -96.33503038, "distance": 45.771494, "ev": 124.64719888998, "la": 83.95865947, "result": "Out", "batterSide": "Right", "year": 2019}, {"direction": -17.95002938, "distance": null, "ev": 108.853307862652, "la": 30.98359552, "result": "Out", "batterSide": "Left", "year": 2019}, {"direction": 9.299400811, "distance": 24.45878981, "ev": 128.085274225435, "la": -2.433046767, "result": "Out", "batterSide": "Right", "year": 2019}, {"direction": 22.12220491, "distance": null, "ev": 102.047469191968, "la": 39.20775252, "result": "Out", "batterSide": "Right", "year": 2019}, {"direction": null, "distance": null, "ev": null, "la": null, "result": "Out", "batterSide": "Right", "year": 2019}, {"direction": 45.66528506, "distance": null, "ev": 134.81038603599, "la": 40.60681947, "result": "Out", "batterSide": "Right", "year": 2019}, {"direction": 35.17722204, "distance": null, "ev": 160.930041522495, "la": 23.08053963, "result": "Double", "batterSide": "Left", "year": 2019}, {"direction": 6.545530443, "distance": null, "ev": 145.737080593924, "la": 45.34574741, "result": "Out", "batterSide": "Left", "year": 2019}, {"direction": -23.80820318, "distance": null, "ev": 125.844477827597, "la": 15.98576157, "result": "Single", "batterSide": "Left", "year": 2019}, {"direction": -96.33503038, "distance": 45.771494, "ev": 124.64719888998, "la": 83.95865947, "result": "Out", "batterSide": "Right", "year": 2019}, {"direction": -17.95002938, "distance": null, "ev": 108.853307862652, "la": 30.98359552, "result": "Out", "batterSide": "Left", "year": 2019}, {"direction": 9.299400811, "distance": 24.45878981, "ev": 128.085274225435, "la": -2.433046767, "result": "Out", "batterSide": "Right", "year": 2019}, {"direction": 22.12220491, "distance": null, "ev": 102.047469191968, "la": 39.20775252, "result": "Out", "batterSide": "Right", "year": 2019}], "zones": [{"zoneId": "outside", "total": 48, "pct": 88.9, "swingPct": 37.5, "whiffPct": 44.4, "avg": 0.0, "gbPct": 0.0, "hardHitPct": 0.0, "byPitchType": {"その他": {"count": 1, "pct": 2.1, "whiffPct": 0, "avg": 0, "gbPct": 0, "hardHitPct": 0}, "ストレート": {"count": 20, "pct": 41.7, "whiffPct": 12.5, "avg": 0, "gbPct": 0, "hardHitPct": 0.0}, "チェンジアップ": {"count": 27, "pct": 56.2, "whiffPct": 70.0, "avg": 0.0, "gbPct": 0.0, "hardHitPct": 0.0}}}, {"zoneId": "2", "total": 2, "pct": 3.7, "swingPct": 0.0, "whiffPct": 0, "avg": 0, "gbPct": 0, "hardHitPct": 0, "byPitchType": {"その他": {"count": 2, "pct": 100.0, "whiffPct": 0, "avg": 0, "gbPct": 0, "hardHitPct": 0}}}, {"zoneId": "5", "total": 2, "pct": 3.7, "swingPct": 0.0, "whiffPct": 0, "avg": 0, "gbPct": 0, "hardHitPct": 0, "byPitchType": {"チェンジアップ": {"count": 2, "pct": 100.0, "whiffPct": 0, "avg": 0, "gbPct": 0, "hardHitPct": 0}}}, {"zoneId": "7", "total": 2, "pct": 3.7, "swingPct": 0.0, "whiffPct": 0, "avg": 0, "gbPct": 0, "hardHitPct": 0, "byPitchType": {"チェンジアップ": {"count": 2, "pct": 100.0, "whiffPct": 0, "avg": 0, "gbPct": 0, "hardHitPct": 0}}}]}