{"team": "東京大学", "batted": [{"direction": -17.220467, "distance": 60.462756, "ev": 135.6508, "la": 11.57453, "result": "Single", "pitchType": "チェンジアップ", "plateLocSide": 0.220604, "plateLocHeight": 0.812222, "batterSide": "Left", "pitcherThrows": "Right", "year": 2022}, {"direction": -47.767429, "distance": 57.531124, "ev": 118.53488, "la": 54.504596, "result": "Out", "pitchType": "ストレート", "plateLocSide": 0.018645, "plateLocHeight": 1.002989, "batterSide": "Left", "pitcherThrows": "Right", "year": 2022}, {"direction": -2.816691, "distance": 43.088242, "ev": 139.00857, "la": 6.843274, "result": "Single", "pitchType": "ストレート", "plateLocSide": 0.07821, "plateLocHeight": 0.578122, "batterSide": "Left", "pitcherThrows": "Right", "year": 2022}, {"direction": -9.351919, "distance": 54.210319, "ev": 141.17651, "la": 7.59838, "result": "Out", "pitchType": "シンカー", "plateLocSide": 0.215139, "plateLocHeight": 0.994792, "batterSide": "Left", "pitcherThrows": "Right", "year": 2022}, {"direction": 10.871209, "distance": 1.389887, "ev": 120.0793, "la": -29.917034, "result": "Out", "pitchType": "シンカー", "plateLocSide": 0.178222, "plateLocHeight": 0.589425, "batterSide": "Left", "pitcherThrows": "Right", "year": 2022}, {"direction": 23.151222, "distance": 1.691322, "ev": 110.0124, "la": -32.959192, "result": "Out", "pitchType": "チェンジアップ", "plateLocSide": 0.234454, "plateLocHeight": 0.798725, "batterSide": "Left", "pitcherThrows": "Right", "year": 2022}, {"direction": 36.376369, "distance": 1.493819, "ev": 115.94671, "la": -37.332098, "result": "Out", "pitchType": "シンカー", "plateLocSide": -0.12459, "plateLocHeight": 0.679929, "batterSide": "Left", "pitcherThrows": "Right", "year": 2022}, {"direction": -17.815371, "distance": 8.984732, "ev": 145.21991, "la": -3.460224, "result": "Out", "pitchType": "チェンジアップ", "plateLocSide": 0.342378, "plateLocHeight": 0.787223, "batterSide": "Left", "pitcherThrows": "Right", "year": 2022}, {"direction": -23.054039, "distance": 77.515837, "ev": 118.25007, "la": 29.356443, "result": "Out", "pitchType": "ストレート", "plateLocSide": 0.076249, "plateLocHeight": 1.210919, "batterSide": "Left", "pitcherThrows": "Left", "year": 2022}, {"direction": 37.947817, "distance": 2.386078, "ev": 109.3132, "la": -22.714514, "result": "Out", "pitchType": "ストレート", "plateLocSide": -0.173977, "plateLocHeight": 0.77625, "batterSide": "Left", "pitcherThrows": "Right", "year": 2022}, {"direction": -20.418373, "distance": 72.853268, "ev": 123.87231, "la": 22.414615, "result": "Single", "pitchType": "スプリット", "plateLocSide": 0.066257, "plateLocHeight": 0.365698, "batterSide": "Left", "pitcherThrows": "Right", "year": 2022}, {"direction": -17.815371, "distance": 8.984732, "ev": 145.21991, "la": -3.460224, "result": "Out", "pitchType": "チェンジアップ", "plateLocSide": 0.342378, "plateLocHeight": 0.787223, "batterSide": "Left", "pitcherThrows": "Right", "year": 2022}, {"direction": -23.054039, "distance": 77.515837, "ev": 118.25007, "la": 29.356443, "result": "Out", "pitchType": "ストレート", "plateLocSide": 0.076249, "plateLocHeight": 1.210919, "batterSide": "Left", "pitcherThrows": "Left", "year": 2022}, {"direction": 37.947817, "distance": 2.386078, "ev": 109.3132, "la": -22.714514, "result": "Out", "pitchType": "ストレート", "plateLocSide": -0.173977, "plateLocHeight": 0.77625, "batterSide": "Left", "pitcherThrows": "Right", "year": 2022}], "impacts": [{"px": 0.227954, "pz": 0.966925, "result": "BallCalled", "pitchType": "カーブ", "pitcherThrows": "Right", "year": 2022}, {"px": 0.265464, "pz": 1.241441, "result": "BallCalled", "pitchType": "チェンジアップ", "pitcherThrows": "Right", "year": 2022}, {"px": 0.220604, "pz": 0.812222, "result": "安打", "pitchType": "チェンジアップ", "pitcherThrows": "Right", "year": 2022}, {"px": -0.223568, "pz": 0.516037, "result": "空振り", "pitchType": "スライダー", "pitcherThrows": "Right", "year": 2022}, {"px": -0.556546, "pz": -0.134613, "result": "BallCalled", "pitchType": "スライダー", "pitcherThrows": "Right", "year": 2022}, {"px": 0.018645, "pz": 1.002989, "result": "凡打", "pitchType": "ストレート", "pitcherThrows": "Right", "year": 2022}, {"px": 0.07821, "pz": 0.578122, "result": "安打", "pitchType": "ストレート", "pitcherThrows": "Right", "year": 2022}, {"px": 0.215139, "pz": 0.994792, "result": "凡打", "pitchType": "シンカー", "pitcherThrows": "Right", "year": 2022}, {"px": 0.413022, "pz": 1.078675, "result": "BallCalled", "pitchType": "シンカー", "pitcherThrows": "Right", "year": 2022}, {"px": 0.178222, "pz": 0.589425, "result": "凡打", "pitchType": "シンカー", "pitcherThrows": "Right", "year": 2022}, {"px": 0.355768, "pz": 0.777392, "result": "StrikeCalled", "pitchType": "スライダー", "pitcherThrows": "Right", "year": 2022}, {"px": 0.234454, "pz": 0.798725, "result": "凡打", "pitchType": "チェンジアップ", "pitcherThrows": "Right", "year": 2022}, {"px": 0.118483, "pz": 0.873851, "result": "StrikeCalled", "pitchType": "カーブ", "pitcherThrows": "Right", "year": 2022}, {"px": 0.062013, "pz": 0.432642, "result": "BallCalled", "pitchType": "ストレート", "pitcherThrows": "Right", "year": 2022}, {"px": 0.385717, "pz": 0.729902, "result": "空振り", "pitchType": "チェンジアップ", "pitcherThrows": "Right", "year": 2022}, {"px": -0.12459, "pz": 0.679929, "result": "凡打", "pitchType": "シンカー", "pitcherThrows": "Right", "year": 2022}, {"px": 0.246759, "pz": 0.679387, "result": "空振り", "pitchType": "カーブ", "pitcherThrows": "Right", "year": 2022}, {"px": 0.123429, "pz": 0.314084, "result": "BallCalled", "pitchType": "シンカー", "pitcherThrows": "Right", "year": 2022}, {"px": 0.282503, "pz": 0.585986, "result": "空振り", "pitchType": "ストレート", "pitcherThrows": "Right", "year": 2022}, {"px": -0.153396, "pz": 0.097715, "result": "空振り", "pitchType": "カーブ", "pitcherThrows": "Right", "year": 2022}, {"px": 0.472897, "pz": 0.978783, "result": "BallCalled", "pitchType": "カーブ", "pitcherThrows": "Right", "year": 2022}, {"px": 0.342378, "pz": 0.787223, "result": "凡打", "pitchType": "チェンジアップ", "pitcherThrows": "Right", "year": 2022}, {"px": -0.357385, "pz": 0.559606, "result": "BallCalled", "pitchType": "チェンジアップ", "pitcherThrows": "Right", "year": 2022}, {"px": 0.207915, "pz": 0.454607, "result": "BallCalled", "pitchType": "チェンジアップ", "pitcherThrows": "Right", "year": 2022}, {"px": 0.141164, "pz": 0.404031, "result": "BallCalled", "pitchType": "シンカー", "pitcherThrows": "Right", "year": 2022}, {"px": 0.566496, "pz": 0.859455, "result": "BallCalled", "pitchType": "シンカー", "pitcherThrows": "Right", "year": 2022}, {"px": 0.086608, "pz": 0.788302, "result": "StrikeCalled", "pitchType": "ストレート", "pitcherThrows": "Left", "year": 2022}, {"px": -0.104968, "pz": 0.953937, "result": "BallCalled", "pitchType": "カーブ", "pitcherThrows": "Left", "year": 2022}, {"px": 0.354852, "pz": 1.111083, "result": "BallCalled", "pitchType": "ストレート", "pitcherThrows": "Left", "year": 2022}, {"px": -0.026975, "pz": 0.776337, "result": "空振り", "pitchType": "ストレート", "pitcherThrows": "Left", "year": 2022}, {"px": 0.076249, "pz": 1.210919, "result": "凡打", "pitchType": "ストレート", "pitcherThrows": "Left", "year": 2022}, {"px": 0.01313, "pz": 0.570004, "result": "StrikeCalled", "pitchType": "カーブ", "pitcherThrows": "Right", "year": 2022}, {"px": 0.157103, "pz": 1.198868, "result": "BallCalled", "pitchType": "カーブ", "pitcherThrows": "Right", "year": 2022}, {"px": 0.339149, "pz": 0.661879, "result": "StrikeCalled", "pitchType": "ストレート", "pitcherThrows": "Right", "year": 2022}, {"px": -0.173977, "pz": 0.77625, "result": "凡打", "pitchType": "ストレート", "pitcherThrows": "Right", "year": 2022}, {"px": -0.041209, "pz": 0.580345, "result": "StrikeCalled", "pitchType": "カーブ", "pitcherThrows": "Right", "year": 2022}, {"px": 0.617806, "pz": 1.34276, "result": "BallCalled", "pitchType": "カーブ", "pitcherThrows": "Right", "year": 2022}, {"px": 0.066257, "pz": 0.365698, "result": "安打", "pitchType": "スプリット", "pitcherThrows": "Right", "year": 2022}, {"px": 0.207971, "pz": 0.233537, "result": "空振り", "pitchType": "カーブ", "pitcherThrows": "Right", "year": 2022}, {"px": 0.379129, "pz": 0.643795, "result": "StrikeCalled", "pitchType": "ストレート", "pitcherThrows": "Right", "year": 2022}, {"px": 0.302264, "pz": -0.013421, "result": "空振り", "pitchType": "スプリット", "pitcherThrows": "Right", "year": 2022}, {"px": 0.099733, "pz": 0.465721, "result": "StrikeCalled", "pitchType": "カーブ", "pitcherThrows": "Right", "year": 2022}, {"px": -0.17683, "pz": 0.3158, "result": "BallCalled", "pitchType": "ストレート", "pitcherThrows": "Right", "year": 2022}, {"px": 0.300333, "pz": 0.43821, "result": "空振り", "pitchType": "スプリット", "pitcherThrows": "Right", "year": 2022}, {"px": -0.10534, "pz": 0.906077, "result": "BallCalled", "pitchType": "カーブ", "pitcherThrows": "Left", "year": 2022}, {"px": 0.297058, "pz": 0.575674, "result": "StrikeCalled", "pitchType": "シンカー", "pitcherThrows": "Left", "year": 2022}, {"px": 0.333011, "pz": 0.664783, "result": "空振り", "pitchType": "ストレート", "pitcherThrows": "Left", "year": 2022}, {"px": -0.321926, "pz": 0.352402, "result": "空振り", "pitchType": "チェンジアップ", "pitcherThrows": "Right", "year": 2022}, {"px": 0.472897, "pz": 0.978783, "result": "BallCalled", "pitchType": "カーブ", "pitcherThrows": "Right", "year": 2022}, {"px": 0.342378, "pz": 0.787223, "result": "凡打", "pitchType": "チェンジアップ", "pitcherThrows": "Right", "year": 2022}, {"px": -0.357385, "pz": 0.559606, "result": "BallCalled", "pitchType": "チェンジアップ", "pitcherThrows": "Right", "year": 2022}, {"px": 0.207915, "pz": 0.454607, "result": "BallCalled", "pitchType": "チェンジアップ", "pitcherThrows": "Right", "year": 2022}, {"px": 0.141164, "pz": 0.404031, "result": "BallCalled", "pitchType": "シンカー", "pitcherThrows": "Right", "year": 2022}, {"px": 0.566496, "pz": 0.859455, "result": "BallCalled", "pitchType": "シンカー", "pitcherThrows": "Right", "year": 2022}, {"px": 0.086608, "pz": 0.788302, "result": "StrikeCalled", "pitchType": "ストレート", "pitcherThrows": "Left", "year": 2022}, {"px": -0.104968, "pz": 0.953937, "result": "BallCalled", "pitchType": "カーブ", "pitcherThrows": "Left", "year": 2022}, {"px": 0.354852, "pz": 1.111083, "result": "BallCalled", "pitchType": "ストレート", "pitcherThrows": "Left", "year": 2022}, {"px": -0.026975, "pz": 0.776337, "result": "空振り", "pitchType": "ストレート", "pitcherThrows": "Left", "year": 2022}, {"px": 0.076249, "pz": 1.210919, "result": "凡打", "pitchType": "ストレート", "pitcherThrows": "Left", "year": 2022}, {"px": 0.01313, "pz": 0.570004, "result": "StrikeCalled", "pitchType": "カーブ", "pitcherThrows": "Right", "year": 2022}, {"px": 0.157103, "pz": 1.198868, "result": "BallCalled", "pitchType": "カーブ", "pitcherThrows": "Right", "year": 2022}, {"px": 0.339149, "pz": 0.661879, "result": "StrikeCalled", "pitchType": "ストレート", "pitcherThrows": "Right", "year": 2022}, {"px": -0.173977, "pz": 0.77625, "result": "凡打", "pitchType": "ストレート", "pitcherThrows": "Right", "year": 2022}]}