{"team": "明治大学", "batted": [{"direction": -23.873961, "distance": 82.383316, "ev": 122.71646, "la": 35.178262, "result": "Out", "pitchType": "チェンジアップ", "plateLocSide": 0.123223, "plateLocHeight": 0.925367, "batterSide": "Left", "pitcherThrows": "Right", "year": 2025}, {"direction": 13.639953, "distance": 1.681707, "ev": 140.63755, "la": -21.907593, "result": "Out", "pitchType": "チェンジアップ", "plateLocSide": 0.081797, "plateLocHeight": 0.458131, "batterSide": "Left", "pitcherThrows": "Right", "year": 2025}, {"direction": -18.596485, "distance": 22.904598, "ev": 139.83649, "la": 2.467229, "result": "Out", "pitchType": "チェンジアップ", "plateLocSide": 0.336986, "plateLocHeight": 0.467931, "batterSide": "Left", "pitcherThrows": "Right", "year": 2025}, {"direction": 21.375538, "distance": 88.375097, "ev": 141.30015, "la": 19.121261, "result": "Out", "pitchType": "ストレート", "plateLocSide": -0.031546, "plateLocHeight": 0.544137, "batterSide": "Left", "pitcherThrows": "Right", "year": 2025}, {"direction": -27.380493, "distance": 7.443093, "ev": 141.39676, "la": -5.277777, "result": "Single", "pitchType": "ストレート", "plateLocSide": 0.148358, "plateLocHeight": 1.048138, "batterSide": "Left", "pitcherThrows": "Right", "year": 2025}, {"direction": -50.319451, "distance": 1.923598, "ev": 38.26136, "la": -23.878577, "result": "Single", "pitchType": "カーブ", "plateLocSide": -0.169848, "plateLocHeight": 0.808548, "batterSide": "Left", "pitcherThrows": "Right", "year": 2026}, {"direction": -23.995624, "distance": 63.935787, "ev": 154.40633, "la": 7.853156, "result": "Single", "pitchType": "ストレート", "plateLocSide": 0.01918, "plateLocHeight": 0.547675, "batterSide": "Left", "pitcherThrows": "Right", "year": 2026}, {"direction": 2.762765, "distance": 0.433885, "ev": 95.91418, "la": -53.15902, "result": "Out", "pitchType": "ストレート", "plateLocSide": 0.132062, "plateLocHeight": 0.355169, "batterSide": "Left", "pitcherThrows": "Right", "year": 2026}, {"direction": null, "distance": null, "ev": 130.80397, "la": 77.835393, "result": "Out", "pitchType": "シンカー", "plateLocSide": 0.05278, "plateLocHeight": 0.877681, "batterSide": "Left", "pitcherThrows": "Right", "year": 2026}, {"direction": 17.276819, "distance": 16.356489, "ev": 158.31454, "la": 0.542881, "result": "Out", "pitchType": "シンカー", "plateLocSide": -0.021931, "plateLocHeight": 0.341062, "batterSide": "Left", "pitcherThrows": "Left", "year": 2026}, {"direction": 8.02466, "distance": 3.777905, "ev": 150.67251, "la": -11.54608, "result": "Out", "pitchType": "ストレート", "plateLocSide": 0.057931, "plateLocHeight": 0.751665, "batterSide": "Left", "pitcherThrows": "Left", "year": 2026}, {"direction": 12.196314, "distance": 35.447226, "ev": 152.42231, "la": 6.382397, "result": "Error", "pitchType": "シンカー", "plateLocSide": 0.085101, "plateLocHeight": 0.518839, "batterSide": "Left", "pitcherThrows": "Left", "year": 2026}], "impacts": [{"px": 0.280075, "pz": 0.853121, "result": "BallCalled", "pitchType": "チェンジアップ", "pitcherThrows": "Right", "year": 2025}, {"px": 0.123223, "pz": 0.925367, "result": "凡打", "pitchType": "チェンジアップ", "pitcherThrows": "Right", "year": 2025}, {"px": -0.058726, "pz": 0.578312, "result": "StrikeCalled", "pitchType": "チェンジアップ", "pitcherThrows": "Right", "year": 2025}, {"px": 0.767712, "pz": 1.337432, "result": "BallCalled", "pitchType": "ストレート", "pitcherThrows": "Right", "year": 2025}, {"px": -0.252852, "pz": 0.013372, "result": "BallCalled", "pitchType": "チェンジアップ", "pitcherThrows": "Right", "year": 2025}, {"px": -0.067127, "pz": 0.377677, "result": "BallCalled", "pitchType": "チェンジアップ", "pitcherThrows": "Right", "year": 2025}, {"px": -0.05159, "pz": 0.49909, "result": "StrikeCalled", "pitchType": "チェンジアップ", "pitcherThrows": "Right", "year": 2025}, {"px": 0.081797, "pz": 0.458131, "result": "凡打", "pitchType": "チェンジアップ", "pitcherThrows": "Right", "year": 2025}, {"px": -0.020816, "pz": -0.128069, "result": "BallCalled", "pitchType": "チェンジアップ", "pitcherThrows": "Right", "year": 2025}, {"px": 0.336986, "pz": 0.467931, "result": "凡打", "pitchType": "チェンジアップ", "pitcherThrows": "Right", "year": 2025}, {"px": -0.365185, "pz": 0.634124, "result": "BallCalled", "pitchType": "ストレート", "pitcherThrows": "Right", "year": 2025}, {"px": 0.703338, "pz": 1.08394, "result": "StrikeCalled", "pitchType": "カーブ", "pitcherThrows": "Right", "year": 2025}, {"px": -0.031546, "pz": 0.544137, "result": "凡打", "pitchType": "ストレート", "pitcherThrows": "Right", "year": 2025}, {"px": -0.127172, "pz": 0.278775, "result": "BallCalled", "pitchType": "ストレート", "pitcherThrows": "Right", "year": 2025}, {"px": -0.241797, "pz": 0.573266, "result": "StrikeCalled", "pitchType": "ストレート", "pitcherThrows": "Right", "year": 2025}, {"px": 0.148358, "pz": 1.048138, "result": "安打", "pitchType": "ストレート", "pitcherThrows": "Right", "year": 2025}, {"px": 0.232794, "pz": 0.558488, "result": "StrikeCalled", "pitchType": "ストレート", "pitcherThrows": "Right", "year": 2026}, {"px": 0.308323, "pz": 0.471964, "result": "BallCalled", "pitchType": "ストレート", "pitcherThrows": "Right", "year": 2026}, {"px": 0.318503, "pz": 0.865582, "result": "StrikeCalled", "pitchType": "カーブ", "pitcherThrows": "Right", "year": 2026}, {"px": 0.514535, "pz": 1.171757, "result": "BallCalled", "pitchType": "ストレート", "pitcherThrows": "Right", "year": 2026}, {"px": -0.169848, "pz": 0.808548, "result": "安打", "pitchType": "カーブ", "pitcherThrows": "Right", "year": 2026}, {"px": -0.240011, "pz": 0.909267, "result": "StrikeCalled", "pitchType": "チェンジアップ", "pitcherThrows": "Right", "year": 2026}, {"px": -0.388226, "pz": 0.419342, "result": "BallCalled", "pitchType": "チェンジアップ", "pitcherThrows": "Right", "year": 2026}, {"px": 0.637025, "pz": 0.652795, "result": "BallCalled", "pitchType": "チェンジアップ", "pitcherThrows": "Right", "year": 2026}, {"px": -0.476755, "pz": 0.746368, "result": "BallCalled", "pitchType": "チェンジアップ", "pitcherThrows": "Right", "year": 2026}, {"px": -0.260397, "pz": 0.09017, "result": "BallCalled", "pitchType": "チェンジアップ", "pitcherThrows": "Right", "year": 2026}, {"px": 0.01918, "pz": 0.547675, "result": "安打", "pitchType": "ストレート", "pitcherThrows": "Right", "year": 2026}, {"px": 0.135427, "pz": 0.664567, "result": "StrikeCalled", "pitchType": "シンカー", "pitcherThrows": "Left", "year": 2026}, {"px": 0.543102, "pz": 0.74967, "result": "BallCalled", "pitchType": "ストレート", "pitcherThrows": "Left", "year": 2026}, {"px": 0.672896, "pz": 0.295644, "result": "BallCalled", "pitchType": "ストレート", "pitcherThrows": "Left", "year": 2026}, {"px": -0.486384, "pz": 1.355034, "result": "BallCalled", "pitchType": "カーブ", "pitcherThrows": "Left", "year": 2026}, {"px": 0.454402, "pz": 0.580089, "result": "BallCalled", "pitchType": "ストレート", "pitcherThrows": "Left", "year": 2026}, {"px": -0.412325, "pz": 0.312335, "result": "BallCalled", "pitchType": "チェンジアップ", "pitcherThrows": "Right", "year": 2026}, {"px": 0.132062, "pz": 0.355169, "result": "凡打", "pitchType": "ストレート", "pitcherThrows": "Right", "year": 2026}, {"px": -0.059326, "pz": 0.292207, "result": "空振り", "pitchType": "スプリット", "pitcherThrows": "Right", "year": 2026}, {"px": 0.05278, "pz": 0.877681, "result": "凡打", "pitchType": "シンカー", "pitcherThrows": "Right", "year": 2026}, {"px": 0.226757, "pz": 0.347404, "result": "BallCalled", "pitchType": "シンカー", "pitcherThrows": "Left", "year": 2026}, {"px": -0.057772, "pz": 0.981121, "result": "BallCalled", "pitchType": "スライダー", "pitcherThrows": "Left", "year": 2026}, {"px": -0.021931, "pz": 0.341062, "result": "凡打", "pitchType": "シンカー", "pitcherThrows": "Left", "year": 2026}, {"px": 0.288756, "pz": 0.677305, "result": "StrikeCalled", "pitchType": "ストレート", "pitcherThrows": "Left", "year": 2026}, {"px": 0.383644, "pz": -0.075028, "result": "BallCalled", "pitchType": "スライダー", "pitcherThrows": "Left", "year": 2026}, {"px": -0.01168, "pz": 1.159119, "result": "BallCalled", "pitchType": "ストレート", "pitcherThrows": "Left", "year": 2026}, {"px": 0.057931, "pz": 0.751665, "result": "凡打", "pitchType": "ストレート", "pitcherThrows": "Left", "year": 2026}, {"px": 0.299955, "pz": 0.315209, "result": "BallCalled", "pitchType": "シンカー", "pitcherThrows": "Left", "year": 2026}, {"px": 0.085101, "pz": 0.518839, "result": "凡打", "pitchType": "シンカー", "pitcherThrows": "Left", "year": 2026}, {"px": 0.407855, "pz": 1.319045, "result": "BallCalled", "pitchType": "ストレート", "pitcherThrows": "Left", "year": 2026}, {"px": 0.180324, "pz": 1.255276, "result": "BallCalled", "pitchType": "ストレート", "pitcherThrows": "Left", "year": 2026}, {"px": 0.200363, "pz": 1.196691, "result": "BallCalled", "pitchType": "ストレート", "pitcherThrows": "Left", "year": 2026}, {"px": -0.328166, "pz": 1.403265, "result": "BallCalled", "pitchType": "ストレート", "pitcherThrows": "Left", "year": 2026}]}